setup.cfg
setup.py
pyramid_iprestrict/__init__.py
pyramid_iprestrict/config.py
pyramid_iprestrict/tweens.py
pyramid_iprestrict.egg-info/PKG-INFO
pyramid_iprestrict.egg-info/SOURCES.txt
pyramid_iprestrict.egg-info/dependency_links.txt
pyramid_iprestrict.egg-info/not-zip-safe
pyramid_iprestrict.egg-info/requires.txt
pyramid_iprestrict.egg-info/top_level.txt
pyramid_iprestrict/tests/__init__.py
pyramid_iprestrict/tests/test_config.py
pyramid_iprestrict/tests/test_tweens.py