Metadata-Version: 1.1
Name: pyramid-iprestrict
Version: 0.1.0
Summary: IP based restriction tween for pyramid
Home-page: https://github.com/xica/pyramid_iprestrict
Author: xica development team
Author-email: info@xica.net
License: MIT
Keywords: web wsgi pyramid ipaddress
Platform: UNKNOWN
Classifier: Development Status :: 3 - Alpha
Classifier: Environment :: Web Environment
Classifier: Framework :: Pyramid
Classifier: Intended Audience :: Developers
Classifier: License :: OSI Approved :: MIT License
Classifier: Operating System :: POSIX :: Linux
Classifier: Programming Language :: Python
Classifier: Topic :: Internet :: WWW/HTTP
Classifier: Topic :: Internet :: WWW/HTTP :: WSGI
